{
	"id": "6974362957",
	"href": "/resourceInventoryManagement/v4/resource/6974362957",
	"name": "SubNetwork=8,ManagedElement=1,GNBCUCPFunction=1,NRCellCU=1",
	"description": "NR Cell Central Unit (CU)",
	"category": "NR",
	"validFor": {
		"startDateTime": "2020-05-18T00:00:00Z",
		"endDateTime": "2020-12-31T23:59:59Z"
	},
	"lifecycleState": "operating",
	"lifecycleSubState": "working",
	"@type": "NRCellCU",
	"@baseType": "ManagedFunction",
	"@schemaLocation": "/resourceInventoryManagement/v4/schema/NRCellCU",
	"version": "0.1",
	"resourceSpecification": {
		"id": "6974362019",
		"href": "/resourceCatalogManagement/v4/resourceSpecification/6974362019",
		"@type": "ResourceFunctionSpecification"
	},
	"resourceCharacteristic": [
		{
			"name": "userLabel",
			"value" : "nr-cell-cu"
		},
		{
			"name": "nCGI",
			"value" : 687194767
		},
		{
			"name": "rRMPolicy",
			"value" : "Platinum"
		}
	],
	"vsDataContainer": [
		{
			"vsDataType": "acmeParam69",
			"vsDataFormatVersion": "acmeParams-v5",
			"vsData": 695
		}
	],
	"resourceRelationship": [],
	"connectionPoint": []
}
